Metadata-Version: 2.1
Name: HDistributions
Version: 0.2
Summary: Gaussian distributions
Home-page: UNKNOWN
Author: Abid Ali Awan
Author-email: abidaliawan@rocketmail.com
License: UNKNOWN
Platform: UNKNOWN
